image_restoration_tools/__init__.py
image_restoration_tools/irt.py
image_restoration_tools/network.py
image_restoration_tools/tool.py
image_restoration_tools/utils.py
image_restoration_tools/.ipynb_checkpoints/irt-checkpoint.py
image_restoration_tools/models/gaussian_blur.pth
image_restoration_tools/models/gaussian_noise.pth
image_restoration_tools/models/jpeg.pth
image_restoration_tools/models/srn/deblur.model.data-00000-of-00001
image_restoration_tools/models/srn/deblur.model.index
image_restoration_tools/models/srn/deblur.model.meta
image_restoration_tools-2.0.4.data/data/deblur.model.data-00000-of-00001
image_restoration_tools-2.0.4.data/data/deblur.model.index
image_restoration_tools-2.0.4.data/data/deblur.model.meta
image_restoration_tools-2.0.4.data/data/gaussian_blur.pth
image_restoration_tools-2.0.4.data/data/gaussian_noise.pth
image_restoration_tools-2.0.4.data/data/jpeg.pth
image_restoration_tools-2.0.4.dist-info/LICENSE
image_restoration_tools-2.0.4.dist-info/METADATA
image_restoration_tools-2.0.4.dist-info/WHEEL
image_restoration_tools-2.0.4.dist-info/top_level.txt
image_restoration_tools-2.0.4.dist-info/zip-safe
image_restoration_tools-2.0.4.dist-info/RECORD
