Metadata-Version: 2.1
Name: image-restoration-tools
Version: 2.0.4
Summary: a package of image restoration by leo
Home-page: https://github.com/zxy110/image_restoration_tools
Author: Leo
Author-email: zxy2019@pku.edu.cn
License: MIT
Platform: UNKNOWN
